capl_file/__init__.py
capl_file/capl_file.py
capl_file-1.0.3.dist-info/LICENSE.txt
capl_file-1.0.3.dist-info/METADATA
capl_file-1.0.3.dist-info/WHEEL
capl_file-1.0.3.dist-info/top_level.txt
capl_file-1.0.3.dist-info/RECORD
